[
    {
        "courseId":1,
        "data":[
            {
                "title":"Index",
                "description":[
                    {
                        "title":"Welcome to Our Course",
                        "link":"https://firebasestorage.googleapis.com/v0/b/e-learning-2020-2021.appspot.com/o/Videos%2FReactJs_1%2FIndex%2FWhat%20Is%20E-Learning_.mp4?alt=media&token=63e6b8ce-b7b7-4dbc-99d7-06d02da79ad1"
                    },
                    {
                        "title":"Introdunction to ReactJs",
                        "link":"https://firebasestorage.googleapis.com/v0/b/e-learning-2020-2021.appspot.com/o/Videos%2FReactJs_1%2FIntroduction%2FReactJS%20Basics%20-%20%231%20What%20is%20React_.mp4?alt=media&token=c5f1bef5-38d3-4f74-a37f-6a165966320b"
                    }
                ]
            },
            {
                "title":"Core Concept",
                "description":[
                    {
                        "title":"What is State?",
                        "link":"https://firebasestorage.googleapis.com/v0/b/e-learning-2020-2021.appspot.com/o/Videos%2FReactJs_1%2FState%20and%20Props%2FReactJS%20Tutorial%20-%2010%20-%20State.mp4?alt=media&token=1cae53af-f9c7-4b68-b0b3-3f960a9aabbc"
                    },
                    {
                        "title":"What is Props?",
                        "link":"https://firebasestorage.googleapis.com/v0/b/e-learning-2020-2021.appspot.com/o/Videos%2FReactJs_1%2FState%20and%20Props%2FReactJS%20Tutorial%20-%209%20-%20Props.mp4?alt=media&token=7f60c629-c766-4611-8df9-e1aa9a843348"
                    },
                    {
                        "title":"State vs Props",
                        "link":"https://firebasestorage.googleapis.com/v0/b/e-learning-2020-2021.appspot.com/o/Videos%2FReactJs_1%2FState%20and%20Props%2FReact%20State%20Vs%20Props.mp4?alt=media&token=ab6a1584-e05d-44ee-85fb-5a7fac97a523"
                    }
                ]
            }     
        ]
    },
    {
        "courseId":2,
        "data":[
            {
                "title":"Index",
                "description":[
                    {
                        "title":"Welcome to Our Course",
                        "link":"https://firebasestorage.googleapis.com/v0/b/e-learning-2020-2021.appspot.com/o/Videos%2FReactJs_1%2FIndex%2FWhat%20Is%20E-Learning_.mp4?alt=media&token=63e6b8ce-b7b7-4dbc-99d7-06d02da79ad1"
                    },
                    {
                        "title":"Introdunction to VueJs",
                        "link":"https://firebasestorage.googleapis.com/v0/b/e-learning-2020-2021.appspot.com/o/Videos%2FVuejs_2%2FIntroduction%2FVue%20JS%20Intro.mp4?alt=media&token=65e191ad-74a3-48bc-b371-f46966faa9c1"
                    }
                ]
            },
            {
                "title":"Core Concept",
                "description":[
                    {
                        "title":"Part 1",
                        "link":"https://firebasestorage.googleapis.com/v0/b/e-learning-2020-2021.appspot.com/o/Videos%2FVuejs_2%2FIntroduction%2FVue%20JS%20Intro.mp4?alt=media&token=65e191ad-74a3-48bc-b371-f46966faa9c1"
                    }
                ]
            }     
        ]
    },
    {
        "courseId":3,
        "data":[
            {
                "title":"Index",
                "description":[
                    {
                        "title":"Welcome to Our Course",
                        "link":"https://firebasestorage.googleapis.com/v0/b/e-learning-2020-2021.appspot.com/o/Videos%2FReactJs_1%2FIndex%2FWhat%20Is%20E-Learning_.mp4?alt=media&token=63e6b8ce-b7b7-4dbc-99d7-06d02da79ad1"
                    }
                ]
            }    
        ]
    },
    {
        "courseId":4,
        "data":[
            {
                "title":"Index",
                "description":[
                    {
                        "title":"Welcome to Our Course",
                        "link":"https://firebasestorage.googleapis.com/v0/b/e-learning-2020-2021.appspot.com/o/Videos%2FReactJs_1%2FIndex%2FWhat%20Is%20E-Learning_.mp4?alt=media&token=63e6b8ce-b7b7-4dbc-99d7-06d02da79ad1"
                    }
                ]
            }    
        ]
    }
    ,
    {
        "courseId":5,
        "data":[
            {
                "title":"Index",
                "description":[
                    {
                        "title":"Welcome to Our Course",
                        "link":"https://firebasestorage.googleapis.com/v0/b/e-learning-2020-2021.appspot.com/o/Videos%2FReactJs_1%2FIndex%2FWhat%20Is%20E-Learning_.mp4?alt=media&token=63e6b8ce-b7b7-4dbc-99d7-06d02da79ad1"
                    }
                ]
            }    
        ]
    },
    {
        "courseId":6,
        "data":[
            {
                "title":"Index",
                "description":[
                    {
                        "title":"Welcome to Our Course",
                        "link":"https://firebasestorage.googleapis.com/v0/b/e-learning-2020-2021.appspot.com/o/Videos%2FReactJs_1%2FIndex%2FWhat%20Is%20E-Learning_.mp4?alt=media&token=63e6b8ce-b7b7-4dbc-99d7-06d02da79ad1"
                    }
                ]
            }    
        ]
    },
    {
        "courseId":7,
        "data":[
            {
                "title":"Index",
                "description":[
                    {
                        "title":"Welcome to Our Course",
                        "link":"https://firebasestorage.googleapis.com/v0/b/e-learning-2020-2021.appspot.com/o/Videos%2FReactJs_1%2FIndex%2FWhat%20Is%20E-Learning_.mp4?alt=media&token=63e6b8ce-b7b7-4dbc-99d7-06d02da79ad1"
                    }
                ]
            }    
        ]
    },
    {
        "courseId":8,
        "data":[
            {
                "title":"Index",
                "description":[
                    {
                        "title":"Welcome to Our Course",
                        "link":"https://firebasestorage.googleapis.com/v0/b/e-learning-2020-2021.appspot.com/o/Videos%2FReactJs_1%2FIndex%2FWhat%20Is%20E-Learning_.mp4?alt=media&token=63e6b8ce-b7b7-4dbc-99d7-06d02da79ad1"
                    }
                ]
            }    
        ]
    }
]